origametry/__init__.py
origametry/fold.py
origametry/helpers.py
origametry/line.py
origametry/point.py
origametry/reflect.py
origametry/show.py
origametry-0.0.6.dist-info/LICENSE
origametry-0.0.6.dist-info/METADATA
origametry-0.0.6.dist-info/WHEEL
origametry-0.0.6.dist-info/top_level.txt
origametry-0.0.6.dist-info/RECORD
