Metadata-Version: 2.1
Name: origametry
Version: 0.0.6
Summary: Package to perform calculations using the Huzita-Justin axioms for 2-dimensional origami
Author: Alastair Stanley
Project-URL: Documentation, https://origametry.readthedocs.io/
Project-URL: Source, https://github.com/optim-ally/origametry.git
Project-URL: Tracker, https://github.com/optim-ally/origametry/issues
Classifier: Development Status :: 3 - Alpha
Classifier: Intended Audience :: Developers
Classifier: Intended Audience :: Education
Classifier: Intended Audience :: Science/Research
Classifier: Topic :: Education
Classifier: Topic :: Scientific/Engineering :: Mathematics
Classifier: License :: OSI Approved :: Apache Software License
Classifier: Operating System :: POSIX :: Linux
Classifier: Operating System :: MacOS
Classifier: Programming Language :: Python :: 3
Classifier: Programming Language :: Python :: 3.9
Classifier: Programming Language :: Python :: 3.10
Classifier: Programming Language :: Python :: 3.11
Classifier: Programming Language :: Python :: 3 :: Only
Requires-Python: >=3.9.0
License-File: LICENSE
Requires-Dist: matplotlib >=3.9.0
Requires-Dist: multimethod >=1.11.2
Requires-Dist: numpy >=1.26.4
Requires-Dist: sympy >=1.12
